flare/__init__.py
flare/cli/arguments.py
flare/cli/flare_logging.py
flare/cli/main.py
flare/cli/run_commands.py
flare/cli/utils.py
flare/src/__init__.py
flare/src/definitions.py
flare/src/fcc_analysis/fcc_analysis_baseclass.py
flare/src/fcc_analysis/fcc_inputfiles_mixin.py
flare/src/fcc_analysis/fcc_production.yaml
flare/src/fcc_analysis/fcc_stages.py
flare/src/fcc_analysis/tasks.py
flare/src/mc_production/generator_specific_methods.py
flare/src/mc_production/mc_production_types.py
flare/src/mc_production/production_types.yaml
flare/src/mc_production/tasks.py
flare/src/pydantic_models/__init__.py
flare/src/pydantic_models/production_types_model.py
flare/src/pydantic_models/user_mcprod_config_model.py
flare/src/pydantic_models/utils.py
flare/src/templates/steering_file.jinja2
flare/src/utils/__init__.py
flare/src/utils/bracket_mappings.py
flare/src/utils/dirs.py
flare/src/utils/jinja2_utils.py
flare/src/utils/logo.py
flare/src/utils/tasks.py
flare/src/utils/yaml.py
hep_flare-0.1.12.dist-info/LICENSE
hep_flare-0.1.12.dist-info/METADATA
hep_flare-0.1.12.dist-info/WHEEL
hep_flare-0.1.12.dist-info/entry_points.txt
hep_flare-0.1.12.dist-info/RECORD
