Metadata-Version: 2.3
Name: hep-flare
Version: 0.1.12
Summary: Framework for streamlining the FCC framework powered by b2luigi
Author: Cameron Harris
Author-email: cameron.harris@adelaide.edu.au
Requires-Python: >=3.9
Classifier: Programming Language :: Python :: 3
Classifier: Programming Language :: Python :: 3.9
Classifier: Programming Language :: Python :: 3.10
Classifier: Programming Language :: Python :: 3.11
Classifier: Programming Language :: Python :: 3.12
Classifier: Programming Language :: Python :: 3.13
Requires-Dist: PyYAML (>=6.0)
Requires-Dist: b2luigi (>=1.2.0)
Requires-Dist: pydantic (<2)
Project-URL: Homepage, https://github.com/CamCoop1/FLARE
